README.md
setup.py
DragonBall/__init__.py
DragonBall/Constants/ScrapCharacter.py
DragonBall/Constants/ScrapFusion.py
DragonBall/Constants/ScrapGames.py
DragonBall/Constants/ScrapPlanet.py
DragonBall/Constants/ScrapSagas.py
DragonBall/Constants/URLS.py
DragonBall/Data/Characters.py
DragonBall/Data/Fusions.py
DragonBall/Data/OutInformation.py
DragonBall/Data/Planets.py
DragonBall/Data/Sagas.py
DragonBall/Data/VideoGames.py
DragonBall/Soup/section.py
DragonBall/Soup/summary.py
DragonBall/Soup/tags.py
Dragon_Ball_API.egg-info/PKG-INFO
Dragon_Ball_API.egg-info/SOURCES.txt
Dragon_Ball_API.egg-info/dependency_links.txt
Dragon_Ball_API.egg-info/requires.txt
Dragon_Ball_API.egg-info/top_level.txt