Metadata-Version: 2.1
Name: Dragon-Ball-API
Version: 1.0.0
Summary: Api unofficial de dragon ball inspirado de la fandom de dragon ball
Home-page: https://github.com/eduardo-nanguelu/Dragon-Ball-API
Author: Eduardo Lopez
Author-email: nanguelulpz@gmail.com
License: MIT
Download-URL: https://github.com/eduardo-nanguelu/Dragon-Ball-API/tarball/0.1
Keywords: Dragon-Ball-Api,Dragon Ball,Api Dragon Ball
Platform: UNKNOWN
